{"Android Multi-Dex Library":{"length":11361,"start":26},"org.jetbrains.kotlin:kotlin-stdlib-jdk7":{"length":11361,"start":11427},"firebase-auth-interop":{"length":3,"start":22810},"play-services-base":{"length":3,"start":22832},"play-services-tasks":{"length":3,"start":22855},"play-services-basement":{"length":3,"start":22881},"AutoValue Annotations":{"length":11361,"start":22906},"Android Support Library fragment":{"length":11361,"start":34300},"Android Support Library core UI":{"length":11361,"start":45693},"Android Support Library core utils":{"length":11361,"start":57089},"Android Support Library loader":{"length":11361,"start":68481},"Android Support Library View Pager":{"length":11361,"start":79877},"Android Support Library Coordinator Layout":{"length":11361,"start":91281},"Android Support Library Drawer Layout":{"length":11361,"start":102680},"Android Support Library Sliding Pane Layout":{"length":11361,"start":114085},"Android Support Library Custom View":{"length":11361,"start":136879},"Android Support Library Async Layout Inflater":{"length":11361,"start":148286},"Android Support Library compat":{"length":11361,"start":159678},"VersionedParcelable and friends":{"length":11361,"start":171071},"Android Support Library collections":{"length":11361,"start":182468},"Android Lifecycle Runtime":{"length":11361,"start":193855},"Android Lifecycle ViewModel":{"length":11361,"start":205244},"Android Lifecycle LiveData":{"length":11361,"start":216632},"Android Lifecycle LiveData Core":{"length":11361,"start":228025},"Android Lifecycle-Common":{"length":11361,"start":239411},"Android Arch-Runtime":{"length":11361,"start":250793},"Android Arch-Common":{"length":11361,"start":262174},"Android Support Library Interpolators":{"length":11361,"start":273573},"Android Support Library Cursor Adapter":{"length":11361,"start":284973},"Android Support Library Document File":{"length":11361,"start":296372},"Android Support Library Local Broadcast Manager":{"length":11361,"start":307781},"Android Support Library Print":{"length":11361,"start":319172},"Android Support Library Annotations":{"length":11361,"start":330569},"org.jetbrains.kotlin:kotlin-stdlib":{"length":11361,"start":341965},"org.jetbrains.kotlin:kotlin-stdlib-common":{"length":11361,"start":353368},"IntelliJ IDEA Annotations":{"length":11361,"start":364755},"firebase-common":{"length":11361,"start":421645},"firebase-common-ktx":{"length":11361,"start":387513},"firebase-storage":{"length":11361,"start":410268}}
